bilibili_mcp_server_full/__init__.py
bilibili_mcp_server_full/server.py
bilibili_mcp_server_full-0.1.2.dist-info/METADATA
bilibili_mcp_server_full-0.1.2.dist-info/WHEEL
bilibili_mcp_server_full-0.1.2.dist-info/entry_points.txt
bilibili_mcp_server_full-0.1.2.dist-info/RECORD
