Metadata-Version: 2.4
Name: bilibili-mcp-server-full
Version: 0.1.2
Summary: Add your description here
Author-email: huanyushi <1174601344@qq.com>
Requires-Python: >=3.10
Requires-Dist: bilibili-api-python>=17.1.4
Requires-Dist: mcp[cli]>=1.6.0
